url_handle-0.3.7.dist-info/METADATA
url_handle-0.3.7.dist-info/WHEEL
url_handle/__init__.py
url_handle/url_handle.abi3.so
url_handle-0.3.7.dist-info/RECORD
