Metadata-Version: 2.4
Name: url_handle
Version: 0.3.7
Classifier: Programming Language :: Rust
Classifier: Programming Language :: Python :: Implementation :: CPython
Classifier: Programming Language :: Python :: Implementation :: PyPy
Requires-Dist: pytest ; extra == 'tests'
Provides-Extra: tests
Requires-Python: >=3.8
